requests_rest_api/__about__.py
requests_rest_api/__init__.py
requests_rest_api/auth.py
requests_rest_api/errors.py
requests_rest_api/http_request_methods.py
requests_rest_api/rest_api.py
requests_rest_api-0.2.4.dist-info/METADATA
requests_rest_api-0.2.4.dist-info/WHEEL
requests_rest_api-0.2.4.dist-info/licenses/LICENSE.txt
requests_rest_api-0.2.4.dist-info/RECORD
