Metadata-Version: 2.1
Name: requests-rest-api
Version: 0.2.4
Summary: The requests-rest-api package contains functions to make REST API calls using the requests package.
Project-URL: Documentation, https://github.com/hbeemster/requests-rest-api#readme
Project-URL: Issues, https://github.com/hbeemster/requests-rest-api/issues
Project-URL: Source, https://github.com/hbeemster/requests-rest-api
Author-email: herbert <dataengineer42@gmail.com>
License-Expression: MIT
License-File: LICENSE.txt
Classifier: Development Status :: 4 - Beta
Classifier: Programming Language :: Python
Classifier: Programming Language :: Python :: 3.7
Classifier: Programming Language :: Python :: 3.8
Classifier: Programming Language :: Python :: 3.9
Classifier: Programming Language :: Python :: 3.10
Classifier: Programming Language :: Python :: 3.11
Classifier: Programming Language :: Python :: Implementation :: CPython
Classifier: Programming Language :: Python :: Implementation :: PyPy
Requires-Python: >=3.7
Requires-Dist: requests
